langgraph/checkpoint/postgres/__init__.py
langgraph/checkpoint/postgres/aio.py
langgraph/checkpoint/postgres/base.py
langgraph/checkpoint/py.typed
gigagraph_checkpoint_postgres-1.0.6.dist-info/METADATA
gigagraph_checkpoint_postgres-1.0.6.dist-info/WHEEL
gigagraph_checkpoint_postgres-1.0.6.dist-info/RECORD
